drf_cli/__init__.py
drf_cli/app.py
drf_cli-0.1.1.dist-info/entry_points.txt
drf_cli-0.1.1.dist-info/LICENSE
drf_cli-0.1.1.dist-info/WHEEL
drf_cli-0.1.1.dist-info/METADATA
drf_cli-0.1.1.dist-info/RECORD
