Metadata-Version: 2.1
Name: drf-cli
Version: 0.1.1
Summary: Tool for creating DRF projects
Author: Patrick Rodrigues
Requires-Python: >=3.8,<4.0
Classifier: Programming Language :: Python :: 3
Classifier: Programming Language :: Python :: 3.8
Classifier: Programming Language :: Python :: 3.9
Requires-Dist: cookiecutter (>=1.7.2,<2.0.0)
Requires-Dist: pyyaml (>=5.3.1,<6.0.0)
Requires-Dist: typer (>=0.2.1,<0.3.0)
